setup.py
dataStructures/__init__.py
finalProj.egg-info/PKG-INFO
finalProj.egg-info/SOURCES.txt
finalProj.egg-info/dependency_links.txt
finalProj.egg-info/top_level.txt