Metadata-Version: 2.1
Name: finalProj
Version: 0.1
Summary: Final Project
Author: Justin Pham, Angelo Troncone
Author-email: justin.pham@ucalgary.ca
